<annotation><filename>TABLE_BHXH3_VATI_3131_56.jpg</filename><folder>TSR PROJECT HOON</folder><path>D:\My Desktop\FINAL PROJECT\TABLE EXTRACTION\VATI-PREPERATION-DATA\Table_Type_BHXH_VATI\TSR\images\TABLE_BHXH3_VATI_3131_56.jpg</path><source><database>Unknown</database></source><size><width>1000</width><height>1000</height><depth>3</depth></size><object><name>table</name><pose>Unspecified</pose><truncated>0</truncated><difficult>0</difficult><bndbox><xmin>35</xmin><ymin>35</ymin><xmax>950</xmax><ymax>1000</ymax></bndbox></object><object><name>table row</name><pose>Unspecified</pose><truncated>0</truncated><difficult>0</difficult><bndbox><xmin>35</xmin><ymin>35</ymin><xmax>950</xmax><ymax>102</ymax></bndbox></object><object><name>table row</name><pose>Unspecified</pose><truncated>0</truncated><difficult>0</difficult><bndbox><xmin>35</xmin><ymin>102</ymin><xmax>950</xmax><ymax>134</ymax></bndbox></object><object><name>table row</name><pose>Unspecified</pose><truncated>0</truncated><difficult>0</difficult><bndbox><xmin>35</xmin><ymin>134</ymin><xmax>950</xmax><ymax>167</ymax></bndbox></object><object><name>table row</name><pose>Unspecified</pose><truncated>0</truncated><difficult>0</difficult><bndbox><xmin>35</xmin><ymin>167</ymin><xmax>950</xmax><ymax>232</ymax></bndbox></object><object><name>table row</name><pose>Unspecified</pose><truncated>0</truncated><difficult>0</difficult><bndbox><xmin>35</xmin><ymin>232</ymin><xmax>950</xmax><ymax>267</ymax></bndbox></object><object><name>table row</name><pose>Unspecified</pose><truncated>0</truncated><difficult>0</difficult><bndbox><xmin>35</xmin><ymin>267</ymin><xmax>950</xmax><ymax>298</ymax></bndbox></object><object><name>table row</name><pose>Unspecified</pose><truncated>0</truncated><difficult>0</difficult><bndbox><xmin>35</xmin><ymin>298</ymin><xmax>950</xmax><ymax>331</ymax></bndbox></object><object><name>table row</name><pose>Unspecified</pose><truncated>0</truncated><difficult>0</difficult><bndbox><xmin>35</xmin><ymin>331</ymin><xmax>950</xmax><ymax>398</ymax></bndbox></object><object><name>table row</name><pose>Unspecified</pose><truncated>0</truncated><difficult>0</difficult><bndbox><xmin>35</xmin><ymin>398</ymin><xmax>950</xmax><ymax>431</ymax></bndbox></object><object><name>table row</name><pose>Unspecified</pose><truncated>0</truncated><difficult>0</difficult><bndbox><xmin>35</xmin><ymin>431</ymin><xmax>950</xmax><ymax>466</ymax></bndbox></object><object><name>table row</name><pose>Unspecified</pose><truncated>0</truncated><difficult>0</difficult><bndbox><xmin>35</xmin><ymin>466</ymin><xmax>950</xmax><ymax>499</ymax></bndbox></object><object><name>table row</name><pose>Unspecified</pose><truncated>0</truncated><difficult>0</difficult><bndbox><xmin>35</xmin><ymin>499</ymin><xmax>950</xmax><ymax>531</ymax></bndbox></object><object><name>table row</name><pose>Unspecified</pose><truncated>0</truncated><difficult>0</difficult><bndbox><xmin>35</xmin><ymin>531</ymin><xmax>950</xmax><ymax>564</ymax></bndbox></object><object><name>table row</name><pose>Unspecified</pose><truncated>0</truncated><difficult>0</difficult><bndbox><xmin>35</xmin><ymin>564</ymin><xmax>950</xmax><ymax>596</ymax></bndbox></object><object><name>table row</name><pose>Unspecified</pose><truncated>0</truncated><difficult>0</difficult><bndbox><xmin>35</xmin><ymin>596</ymin><xmax>950</xmax><ymax>628</ymax></bndbox></object><object><name>table row</name><pose>Unspecified</pose><truncated>0</truncated><difficult>0</difficult><bndbox><xmin>35</xmin><ymin>628</ymin><xmax>950</xmax><ymax>662</ymax></bndbox></object><object><name>table row</name><pose>Unspecified</pose><truncated>0</truncated><difficult>0</difficult><bndbox><xmin>35</xmin><ymin>662</ymin><xmax>950</xmax><ymax>696</ymax></bndbox></object><object><name>table row</name><pose>Unspecified</pose><truncated>0</truncated><difficult>0</difficult><bndbox><xmin>35</xmin><ymin>696</ymin><xmax>950</xmax><ymax>764</ymax></bndbox></object><object><name>table row</name><pose>Unspecified</pose><truncated>0</truncated><difficult>0</difficult><bndbox><xmin>35</xmin><ymin>764</ymin><xmax>950</xmax><ymax>798</ymax></bndbox></object><object><name>table row</name><pose>Unspecified</pose><truncated>0</truncated><difficult>0</difficult><bndbox><xmin>35</xmin><ymin>798</ymin><xmax>950</xmax><ymax>832</ymax></bndbox></object><object><name>table row</name><pose>Unspecified</pose><truncated>0</truncated><difficult>0</difficult><bndbox><xmin>35</xmin><ymin>832</ymin><xmax>950</xmax><ymax>864</ymax></bndbox></object><object><name>table row</name><pose>Unspecified</pose><truncated>0</truncated><difficult>0</difficult><bndbox><xmin>35</xmin><ymin>864</ymin><xmax>950</xmax><ymax>899</ymax></bndbox></object><object><name>table row</name><pose>Unspecified</pose><truncated>0</truncated><difficult>0</difficult><bndbox><xmin>35</xmin><ymin>899</ymin><xmax>950</xmax><ymax>934</ymax></bndbox></object><object><name>table row</name><pose>Unspecified</pose><truncated>0</truncated><difficult>0</difficult><bndbox><xmin>35</xmin><ymin>934</ymin><xmax>950</xmax><ymax>965</ymax></bndbox></object><object><name>table row</name><pose>Unspecified</pose><truncated>0</truncated><difficult>0</difficult><bndbox><xmin>35</xmin><ymin>965</ymin><xmax>950</xmax><ymax>1000</ymax></bndbox></object><object><name>table column</name><pose>Unspecified</pose><truncated>0</truncated><difficult>0</difficult><bndbox><xmin>35</xmin><ymin>35</ymin><xmax>113</xmax><ymax>1000</ymax></bndbox></object><object><name>table column</name><pose>Unspecified</pose><truncated>0</truncated><difficult>0</difficult><bndbox><xmin>113</xmin><ymin>35</ymin><xmax>701</xmax><ymax>1000</ymax></bndbox></object><object><name>table column</name><pose>Unspecified</pose><truncated>0</truncated><difficult>0</difficult><bndbox><xmin>701</xmin><ymin>35</ymin><xmax>766</xmax><ymax>1000</ymax></bndbox></object><object><name>table column</name><pose>Unspecified</pose><truncated>0</truncated><difficult>0</difficult><bndbox><xmin>766</xmin><ymin>35</ymin><xmax>830</xmax><ymax>1000</ymax></bndbox></object><object><name>table column</name><pose>Unspecified</pose><truncated>0</truncated><difficult>0</difficult><bndbox><xmin>830</xmin><ymin>35</ymin><xmax>888</xmax><ymax>1000</ymax></bndbox></object><object><name>table column</name><pose>Unspecified</pose><truncated>0</truncated><difficult>0</difficult><bndbox><xmin>888</xmin><ymin>35</ymin><xmax>950</xmax><ymax>1000</ymax></bndbox></object><object><name>table column header</name><pose>Unspecified</pose><truncated>0</truncated><difficult>0</difficult><bndbox><xmin>35</xmin><ymin>35</ymin><xmax>950</xmax><ymax>167</ymax></bndbox></object><object><name>table spanning cell</name><pose>Unspecified</pose><truncated>0</truncated><difficult>0</difficult><bndbox><xmin>701</xmin><ymin>35</ymin><xmax>950</xmax><ymax>102</ymax></bndbox></object><object><name>table spanning cell</name><pose>Unspecified</pose><truncated>0</truncated><difficult>0</difficult><bndbox><xmin>35</xmin><ymin>102</ymin><xmax>113</xmax><ymax>167</ymax></bndbox></object><object><name>table spanning cell</name><pose>Unspecified</pose><truncated>0</truncated><difficult>0</difficult><bndbox><xmin>113</xmin><ymin>102</ymin><xmax>701</xmax><ymax>167</ymax></bndbox></object><object><name>table spanning cell</name><pose>Unspecified</pose><truncated>0</truncated><difficult>0</difficult><bndbox><xmin>701</xmin><ymin>102</ymin><xmax>950</xmax><ymax>134</ymax></bndbox></object></annotation>